logging_config.py
setup.py
logging_config.egg-info/PKG-INFO
logging_config.egg-info/SOURCES.txt
logging_config.egg-info/dependency_links.txt
logging_config.egg-info/top_level.txt
logging_config.egg-info/zip-safe